agentstr/__init__.py
agentstr/logger.py
agentstr/models.py
agentstr/nostr_client.py
agentstr/scheduler.py
agentstr/utils.py
agentstr/agents/__init__.py
agentstr/agents/agentstr.py
agentstr/agents/nostr_agent.py
agentstr/agents/nostr_agent_server.py
agentstr/agents/nostr_rag.py
agentstr/agents/providers/__init__.py
agentstr/agents/providers/agno.py
agentstr/agents/providers/dspy.py
agentstr/agents/providers/google.py
agentstr/agents/providers/langgraph.py
agentstr/agents/providers/openai.py
agentstr/agents/providers/pydantic.py
agentstr/cli/__init__.py
agentstr/cli/providers.py
agentstr/cli/providers_aws.py
agentstr/cli/providers_azure.py
agentstr/cli/providers_docker.py
agentstr/cli/providers_gcp.py
agentstr/commands/__init__.py
agentstr/commands/base.py
agentstr/commands/commands.py
agentstr/database/__init__.py
agentstr/database/base.py
agentstr/database/postgres.py
agentstr/database/sqlite.py
agentstr/mcp/__init__.py
agentstr/mcp/nostr_mcp_client.py
agentstr/mcp/nostr_mcp_server.py
agentstr/mcp/providers/__init__.py
agentstr/mcp/providers/agno.py
agentstr/mcp/providers/dspy.py
agentstr/mcp/providers/google.py
agentstr/mcp/providers/langgraph.py
agentstr/mcp/providers/openai.py
agentstr/mcp/providers/pydantic.py
agentstr/relays/__init__.py
agentstr/relays/nwc_relay.py
agentstr/relays/relay.py
agentstr/relays/relay_manager.py
agentstr_sdk-0.6.15.dist-info/licenses/LICENSE
agentstr_sdk-0.6.15.dist-info/METADATA
agentstr_sdk-0.6.15.dist-info/WHEEL
agentstr_sdk-0.6.15.dist-info/entry_points.txt
agentstr_sdk-0.6.15.dist-info/top_level.txt
agentstr_sdk-0.6.15.dist-info/RECORD
